eurekaroom/__init__.py
eurekaroom/args.py
eurekaroom/config.py
eurekaroom/createService.py
eurekaroom/node.py
eurekaroom/routes.py
eurekaroom/video.py
eurekaroom/installScripts/eurekaroom.service
eurekaroom/templates/404.html
eurekaroom/templates/background.html
eurekaroom/templates/backgrounds.html
eurekaroom/templates/base.html
eurekaroom/templates/images.html
eurekaroom/templates/index.html
eurekaroom/templates/listmedia.html
eurekaroom/templates/media.html
eurekaroom/templates/videos.html
eurekaroom-1.0.2.data/scripts/ecmd
eurekaroom-1.0.2.dist-info/LICENSE
eurekaroom-1.0.2.dist-info/METADATA
eurekaroom-1.0.2.dist-info/WHEEL
eurekaroom-1.0.2.dist-info/top_level.txt
eurekaroom-1.0.2.dist-info/RECORD
