Metadata-Version: 2.1
Name: eurekaroom
Version: 1.0.2
Summary: A command-processor and RESTful server for use in escapenodes on RaspberryPi systems.
Home-page: https://gitlab.com/growlf/eurekaroom.git
Author: Daniel Eguia
Author-email: eguiamotion@gmail.com
License: License :: OSI Approved :: GNU General Public License v3 (GPLv3)
Platform: UNKNOWN
Classifier: Programming Language :: Python :: 3
Classifier: Operating System :: POSIX :: Linux
Requires-Python: >=3.0.0
Requires-Dist: click (==7.0)
Requires-Dist: configparser (==4.0.2)
Requires-Dist: dbus-python (==1.2.16)
Requires-Dist: decorator (==4.4.1)
Requires-Dist: elevate (==0.1.3)
Requires-Dist: evento (==1.0.2)
Requires-Dist: flask (==1.1.1)
Requires-Dist: itsdangerous (==1.1.0)
Requires-Dist: jinja2 (==2.11.1)
Requires-Dist: markupsafe (==1.1.1)
Requires-Dist: omxplayer-wrapper (==0.3.2)
Requires-Dist: pathlib2 (==2.3.5)
Requires-Dist: pillow (==7.0.0)
Requires-Dist: python-magic (==0.4.15)
Requires-Dist: rpi.gpio (==0.7.0)
Requires-Dist: six (==1.14.0)
Requires-Dist: systemd-unit (==1.0.5)
Requires-Dist: werkzeug (==1.0.0)
